Workbook

Sheet 前提
A1: AI映像制作事業 — 予算モデル(保守版)
A2: 単位: 万円 / 1年目 = 2026年10月〜2027年9月
A4: 凡例
A5: 青字 | B5: 入力セル。ここを書き換える
A6: 黒字 | B6: 計算式。編集しない
A7: 緑字 | B7: 他シートへの参照
A8: 黄色の網掛け | B8: 最重要の前提。まずここを検証する
A10: シナリオ
A11: シナリオ選択(1=楽観 / 2=標準 / 3=実行可能版) | B11: 3 | C11: ← 1〜3 を入れると各シートの金額が切り替わります
A13: 調達
A14: 資本金(自己資金) | B14: 800 | C14: 設立時に払込
A15: 創業融資 | B15: 2000 | C15: 公庫 + 制度融資の協調
A16: 融資の着金月(1=2026/10) | B16: 2 | C16: 申込から1〜1.5ヶ月
A17: 融資金利(年) | B17: 0.03 | C17: 公庫 創業期・無担保の想定
A18: 目標バッファ(月数) | B18: 3 | C18: 1年目末に残したい固定費の月数
A20: 単価・入金
A21: 平均単価(1本) | B21: 48 | C21: 企業発注の中央値54万より保守的
A22: 入金サイト(ヶ月) | B22: 1 | C22: 納品の翌月末入金
A23: 予備費率(初期費用に対して) | B23: 0.15 | C23: 創業期は必ず想定外が出る。15〜20%
A25: 変動費 — 1本あたり
A26: 項目 | B26: 楽観 | C26: 標準 | D26: 実行可能版 | E26: 採用額 | F26: 備考
A27: 個人クリエイターへの支払 | B27: 12 | C27: 13 | D27: 13 | E27: =INDEX(B27:D27,$B$11) -> 13 | F27: Bランク基準。P0の有償テストで実測する
A28: 一次レビュー報酬(Aランク) | B28: 3 | C28: 3 | D28: 3 | E28: =INDEX(B28:D28,$B$11) -> 3 | F28: 品質を人で担保する部分。削らない
A29: AIツール従量 | B29: 1.5 | C29: 2 | D29: 2 | E29: =INDEX(B29:D29,$B$11) -> 2 | F29: やり直しが発生する
A30: 素材・音源ライセンス | B30: 0.5 | C30: 1 | D30: 1 | E30: =INDEX(B30:D30,$B$11) -> 1 | F30: 商用利用可のもの
A31: 品質バッファ | B31: 1.5 | C31: 2 | D31: 2 | E31: =INDEX(B31:D31,$B$11) -> 2 | F31: 作り直し・追加アサイン
A32: 為替バッファ | B32: 0 | C32: 1 | D32: 1 | E32: =INDEX(B32:D32,$B$11) -> 1 | F32: 人民元建て ±5%
A33: 1本あたり原価 合計 | B33: =SUM(B27:B32) -> 18.5 | C33: =SUM(C27:C32) -> 22 | D33: =SUM(D27:D32) -> 22 | E33: =SUM(E27:E32) -> 22
A34: 粗利率 | E34: =1-E33/$B$21 -> 0.54166667 | F34: 1本原価 ÷ 平均単価 を 1 から引いた値

Sheet 初期費用
A1: A. 初期費用
A2: 単位: 万円 / 発生月は 1=2026年10月 … 12=2027年9月
A4: 項目 | B4: 発生月 | C4: 楽観 | D4: 標準 | E4: 実行可能版 | F4: 採用額 | G4: 備考
A5: 法人設立 | B5: 1 | C5: 21 | D5: 31 | E5: 31 | F5: =INDEX(C5:E5,前提!$B$11) -> 31 | G5: 定款認証5 + 登録免許税15 + 印鑑2 + 司法書士8
A6: 事務所・什器 | B6: 1 | C6: 10 | D6: 20 | E6: 20 | F6: =INDEX(C6:E6,前提!$B$11) -> 20 | G6: レンタルオフィス初期 + 什器
A7: 渡航・クリエイター選定 | B7: 1 | C7: 54 | D7: 80 | E7: 80 | F7: =INDEX(C7:E7,前提!$B$11) -> 80 | G7: 有償テスト課題 + 渡航2回
A8: 機材 | B8: 2 | C8: 55 | D8: 90 | E8: 90 | F8: =INDEX(C8:E8,前提!$B$11) -> 90 | G8: PC2台 + モニター + ストレージ + 予備
A9: サンプル制作 | B9: 2 | C9: 37 | D9: 90 | E9: 70 | F9: =INDEX(C9:E9,前提!$B$11) -> 70 | G9: Aランクで作る。営業の武器なので削らない
A10: ブランド・LP | B10: 2 | C10: 45 | D10: 115 | E10: 75 | F10: =INDEX(C10:E10,前提!$B$11) -> 75 | G10: LP + ロゴVI + 会社案内
A11: 採用 | B11: 2 | C11: 100 | D11: 300 | E11: 150 | F11: =INDEX(C11:E11,前提!$B$11) -> 150 | G11: エージェントは年収の30〜35%
A12: 知的財産 | B12: 3 | C12: 115 | D12: 190 | E12: 110 | F12: =INDEX(C12:E12,前提!$B$11) -> 110 | G12: 弁理士相談 + 特許出願 + 商標
A13: データ基盤 | B13: 3 | C13: 40 | D13: 150 | E13: 50 | F13: =INDEX(C13:E13,前提!$B$11) -> 50 | G13: 実行可能版は最小構成から段階的に
A14: 専門家(税理士・弁護士・社労士) | B14: 3 | C14: 30 | D14: 95 | E14: 95 | F14: =INDEX(C14:E14,前提!$B$11) -> 95 | G14: 中国法の弁護士70万を含む。削らない
A15: 小計 | C15: =SUM(C5:C14) -> 507 | D15: =SUM(D5:D14) -> 1161 | E15: =SUM(E5:E14) -> 771 | F15: =SUM(F5:F14) -> 771
A16: 予備費 | B16: 3 | C16: =C15*前提!$B$23 -> 76.05 | D16: =D15*前提!$B$23 -> 174.15 | E16: =E15*前提!$B$23 -> 115.65 | F16: =F15*前提!$B$23 -> 115.65 | G16: 初期費用の15%。これがないと必ず途中で足りなくなる
A17: 合計 | C17: =C15+C16 -> 583.05 | D17: =D15+D16 -> 1335.15 | E17: =E15+E16 -> 886.65 | F17: =F15+F16 -> 886.65

Sheet 月次固定費
A1: B. 月次固定費
A2: 単位: 万円 / 開始月は 1=2026年10月。役員報酬・採用の開始月を変えると資金繰りが動きます
A4: 項目 | B4: 開始月 | C4: 楽観 | D4: 標準 | E4: 実行可能版 | F4: 採用額 | G4: 備考
A5: 役員報酬 | B5: 3 | C5: 35 | D5: 50 | E5: 50 | F5: =INDEX(C5:E5,前提!$B$11) -> 50 | G5: 定期同額給与。設立時に決めた額が1年固定
A6: 営業1名(給与+賞与+法定福利) | B6: 4 | C6: 48 | D6: 60 | E6: 60 | F6: =INDEX(C6:E6,前提!$B$11) -> 60 | G6: 年収550〜650万を月割
A7: 制作ディレクター1名(同上) | B7: 7 | C7: 48 | D7: 60 | E7: 60 | F7: =INDEX(C7:E7,前提!$B$11) -> 60 | G7: 実行可能版は2027年4月採用。それまで代表が兼務
A8: レンタルオフィス | B8: 1 | C8: 8 | D8: 15 | E8: 12 | F8: =INDEX(C8:E8,前提!$B$11) -> 12
A9: 通信・水道光熱 | B9: 1 | C9: 2 | D9: 3 | E9: 3 | F9: =INDEX(C9:E9,前提!$B$11) -> 3
A10: 会計・税務顧問 | B10: 1 | C10: 4 | D10: 6 | E10: 6 | F10: =INDEX(C10:E10,前提!$B$11) -> 6 | G10: 国際税務が絡むと上がる
A11: 給与計算・労務 | B11: 1 | C11: 1 | D11: 2 | E11: 2 | F11: =INDEX(C11:E11,前提!$B$11) -> 2
A12: クラウド・SaaS | B12: 1 | C12: 3 | D12: 5 | E12: 5 | F12: =INDEX(C12:E12,前提!$B$11) -> 5
A13: AI API 利用料 | B13: 1 | C13: 3 | D13: 5 | E13: 5 | F13: =INDEX(C13:E13,前提!$B$11) -> 5 | G13: 案件数に応じて増える
A14: ストレージ・データ転送 | B14: 1 | C14: 2 | D14: 4 | E14: 4 | F14: =INDEX(C14:E14,前提!$B$11) -> 4 | G14: 映像は重い。想定の2〜3倍になりやすい
A15: 営業活動費 | B15: 1 | C15: 10 | D15: 15 | E15: 15 | F15: =INDEX(C15:E15,前提!$B$11) -> 15
A16: 送金手数料 | B16: 1 | C16: 1 | D16: 2 | E16: 2 | F16: =INDEX(C16:E16,前提!$B$11) -> 2 | G16: 月2回の締めで一括処理する前提
A17: 損害賠償責任保険 | B17: 1 | C17: 1 | D17: 2 | E17: 2 | F17: =INDEX(C17:E17,前提!$B$11) -> 2
A18: 自社チャンネル投資(P2: 月10本) | B18: 4 | C18: 20 | D18: 20 | E18: 20 | F18: =INDEX(C18:E18,前提!$B$11) -> 20 | G18: 2027年1月開始。営業実績づくり + 市場反応データ(PLATFORM_REVENUE.md)
A19: 自社チャンネル投資(P3拡大分) | B19: 7 | C19: 25 | D19: 25 | E19: 25 | F19: =INDEX(C19:E19,前提!$B$11) -> 25 | G19: 2027年4月に月20本へ拡大。上記と合わせて月45万になる
A20: フル体制での月次固定費 | C20: =SUM(C5:C19) -> 211 | D20: =SUM(D5:D19) -> 274 | E20: =SUM(E5:E19) -> 271 | F20: =SUM(F5:F19) -> 271
A22: 損益分岐 月商 | F22: =F20/前提!$E$34 -> 500.30769 | G22: フル体制の固定費 ÷ 粗利率
A23: 損益分岐 月間本数 | F23: =F22/前提!$B$21 -> 10.423077 | G23: 損益分岐月商 ÷ 平均単価
A25: うち 自社チャンネル投資 | F25: =SUM(F18:F19) -> 45 | G25: 営業のための投資。上の損益分岐にはこれも含まれています
A26: 損益分岐 月間本数(チャンネル投資を除く) | F26: =(F20-F25)/前提!$E$34/前提!$B$21 -> 8.6923077 | G26: チャンネルを止めた場合の損益分岐。撤退判断のときに見る数字

Sheet 資金繰り
A1: C. 月次資金繰り(1年目)
A2: 単位: 万円 / 受注本数(6行目)を書き換えると全体が動きます
A4: 月 | B4: 1 | C4: 2 | D4: 3 | E4: 4 | F4: 5 | G4: 6 | H4: 7 | I4: 8 | J4: 9 | K4: 10 | L4: 11 | M4: 12
A5: 年月 | B5: 2026/10 | C5: 2026/11 | D5: 2026/12 | E5: 2027/1 | F5: 2027/2 | G5: 2027/3 | H5: 2027/4 | I5: 2027/5 | J5: 2027/6 | K5: 2027/7 | L5: 2027/8 | M5: 2027/9
A6: 受注・納品本数 | B6: 0 | C6: 0 | D6: 0 | E6: 1 | F6: 2 | G6: 2 | H6: 3 | I6: 3 | J6: 4 | K6: 4 | L6: 5 | M6: 5 | O6: ← 青字・黄色。ここが最上位のドライバー
A7: 売上高 | B7: =B6*前提!$B$21 -> 0 | C7: =C6*前提!$B$21 -> 0 | D7: =D6*前提!$B$21 -> 0 | E7: =E6*前提!$B$21 -> 48 | F7: =F6*前提!$B$21 -> 96 | G7: =G6*前提!$B$21 -> 96 | H7: =H6*前提!$B$21 -> 144 | I7: =I6*前提!$B$21 -> 144 | ... M7: =M6*前提!$B$21 -> 240
A9: 入金(売上・翌月末) | B9: 0 | C9: =B7 -> 0 | D9: =C7 -> 0 | E9: =D7 -> 0 | F9: =E7 -> 48 | G9: =F7 -> 96 | H9: =G7 -> 96 | I9: =H7 -> 144 | J9: =I7 -> 144 | ... M9: =L7 -> 240
A10: 資本金の払込 | B10: =前提!$B$14 -> 800 | C10: 0 | D10: 0 | E10: 0 | F10: 0 | G10: 0 | H10: 0 | I10: 0 | J10: 0 | K10: 0 | L10: 0 | M10: 0
A11: 融資の着金 | B11: =IF(B4=前提!$B$16,前提!$B$15,0) -> 0 | C11: =IF(C4=前提!$B$16,前提!$B$15,0) -> 2000 | D11: =IF(D4=前提!$B$16,前提!$B$15,0) -> 0 | E11: =IF(E4=前提!$B$16,前提!$B$15,0) -> 0 | F11: =IF(F4=前提!$B$16,前提!$B$15,0) -> 0 | G11: =IF(G4=前提!$B$16,前提!$B$15,0) -> 0 | H11: =IF(H4=前提!$B$16,前提!$B$15,0) -> 0 | I11: =IF(I4=前提!$B$16,前提!$B$15,0) -> 0 | ... M11: =IF(M4=前提!$B$16,前提!$B$15,0) -> 0
A12: 入金 合計 | B12: =SUM(B9:B11) -> 800 | C12: =SUM(C9:C11) -> 2000 | D12: =SUM(D9:D11) -> 0 | E12: =SUM(E9:E11) -> 0 | F12: =SUM(F9:F11) -> 48 | G12: =SUM(G9:G11) -> 96 | H12: =SUM(H9:H11) -> 96 | I12: =SUM(I9:I11) -> 144 | ... M12: =SUM(M9:M11) -> 240
A14: 初期費用 | B14: =SUMIF(初期費用!$B$5:$B$17,B4,初期費用!$F$5:$F$17) -> 131 | C14: =SUMIF(初期費用!$B$5:$B$17,C4,初期費用!$F$5:$F$17) -> 385 | D14: =SUMIF(初期費用!$B$5:$B$17,D4,初期費用!$F$5:$F$17) -> 370.65 | E14: =SUMIF(初期費用!$B$5:$B$17,E4,初期費用!$F$5:$F$17) -> 0 | F14: =SUMIF(初期費用!$B$5:$B$17,F4,初期費用!$F$5:$F$17) -> 0 | G14: =SUMIF(初期費用!$B$5:$B$17,G4,初期費用!$F$5:$F$17) -> 0 | H14: =SUMIF(初期費用!$B$5:$B$17,H4,初期費用!$F$5:$F$17) -> 0 | I14: =SUMIF(初期費用!$B$5:$B$17,I4,初期費用!$F$5:$F$17) -> 0 | ... M14: =SUMIF(初期費用!$B$5:$B$17,M4,初期費用!$F$5:$F$17) -> 0
A15: 月次固定費 | B15: =SUMIF(月次固定費!$B$5:$B$19,"<="&B4,月次固定費!$F$5:$F$19) -> 56 | C15: =SUMIF(月次固定費!$B$5:$B$19,"<="&C4,月次固定費!$F$5:$F$19) -> 56 | D15: =SUMIF(月次固定費!$B$5:$B$19,"<="&D4,月次固定費!$F$5:$F$19) -> 106 | E15: =SUMIF(月次固定費!$B$5:$B$19,"<="&E4,月次固定費!$F$5:$F$19) -> 186 | F15: =SUMIF(月次固定費!$B$5:$B$19,"<="&F4,月次固定費!$F$5:$F$19) -> 186 | G15: =SUMIF(月次固定費!$B$5:$B$19,"<="&G4,月次固定費!$F$5:$F$19) -> 186 | H15: =SUMIF(月次固定費!$B$5:$B$19,"<="&H4,月次固定費!$F$5:$F$19) -> 271 | I15: =SUMIF(月次固定費!$B$5:$B$19,"<="&I4,月次固定費!$F$5:$F$19) -> 271 | ... M15: =SUMIF(月次固定費!$B$5:$B$19,"<="&M4,月次固定費!$F$5:$F$19) -> 271
A16: 変動費(制作原価) | B16: =B6*前提!$E$33 -> 0 | C16: =C6*前提!$E$33 -> 0 | D16: =D6*前提!$E$33 -> 0 | E16: =E6*前提!$E$33 -> 22 | F16: =F6*前提!$E$33 -> 44 | G16: =G6*前提!$E$33 -> 44 | H16: =H6*前提!$E$33 -> 66 | I16: =I6*前提!$E$33 -> 66 | ... M16: =M6*前提!$E$33 -> 110
A17: 支払利息 | B17: =IF(B4>=前提!$B$16,前提!$B$15*前提!$B$17/12,0) -> 0 | C17: =IF(C4>=前提!$B$16,前提!$B$15*前提!$B$17/12,0) -> 5 | D17: =IF(D4>=前提!$B$16,前提!$B$15*前提!$B$17/12,0) -> 5 | E17: =IF(E4>=前提!$B$16,前提!$B$15*前提!$B$17/12,0) -> 5 | F17: =IF(F4>=前提!$B$16,前提!$B$15*前提!$B$17/12,0) -> 5 | G17: =IF(G4>=前提!$B$16,前提!$B$15*前提!$B$17/12,0) -> 5 | H17: =IF(H4>=前提!$B$16,前提!$B$15*前提!$B$17/12,0) -> 5 | I17: =IF(I4>=前提!$B$16,前提!$B$15*前提!$B$17/12,0) -> 5 | ... M17: =IF(M4>=前提!$B$16,前提!$B$15*前提!$B$17/12,0) -> 5
A18: 支出 合計 | B18: =SUM(B14:B17) -> 187 | C18: =SUM(C14:C17) -> 446 | D18: =SUM(D14:D17) -> 481.65 | E18: =SUM(E14:E17) -> 213 | F18: =SUM(F14:F17) -> 235 | G18: =SUM(G14:G17) -> 235 | H18: =SUM(H14:H17) -> 342 | I18: =SUM(I14:I17) -> 342 | ... M18: =SUM(M14:M17) -> 386
A20: 月次収支 | B20: =B12-B18 -> 613 | C20: =C12-C18 -> 1554 | D20: =D12-D18 -> -481.65 | E20: =E12-E18 -> -213 | F20: =F12-F18 -> -187 | G20: =G12-G18 -> -139 | H20: =H12-H18 -> -246 | I20: =I12-I18 -> -198 | ... M20: =M12-M18 -> -146
A21: 月末残高 | B21: =B20 -> 613 | C21: =B21+C20 -> 2167 | D21: =C21+D20 -> 1685.35 | E21: =D21+E20 -> 1472.35 | F21: =E21+F20 -> 1285.35 | G21: =F21+G20 -> 1146.35 | H21: =G21+H20 -> 900.35 | I21: =H21+I20 -> 702.35 | J21: =I21+J20 -> 482.35 | ... M21: =L21+M20 -> -29.65
A23: 最低残高 | B23: =MIN(B21:M21) -> -29.65
A24: 最低残高の月 | B24: =INDEX(B5:M5,MATCH(B23,B21:M21,0)) -> 2027/9
A25: 1年目の受注 合計 | B25: =SUM(B6:M6) -> 29
A26: 1年目の売上 合計 | B26: =SUM(B7:M7) -> 1392

Sheet 必要調達
A1: D. 必要調達額
A2: 単位: 万円
A4: 初期費用(予備費込み) | B4: =初期費用!F17 -> 886.65 | C4: 選択シナリオ
A5: フル体制の月次固定費 | B5: =月次固定費!F20 -> 271
A6: 損益分岐 月間本数 | B6: =月次固定費!F23 -> 10.423077
A8: 現在の調達額(資本金 + 融資) | B8: =前提!B14+前提!B15 -> 2800
A9: 1年目の最低残高 | B9: =資金繰り!B23 -> -29.65 | C9: マイナスなら資金が尽きる
A10: 最低残高の月 | B10: =資金繰り!B24 -> 2027/9
A11: 1年目末の残高 | B11: =資金繰り!M21 -> -29.65
A13: 目標バッファ(固定費 × 月数) | B13: =月次固定費!F20*前提!B18 -> 813 | C13: 1年目末に残したい額
A14: 追加で必要な調達 | B14: =MAX(0,月次固定費!F20*前提!B18-資金繰り!B23) -> 842.65 | C14: 最低残高を目標バッファまで引き上げる額
A15: 推奨する調達総額 | B15: =B8+B14 -> 3642.65 | C15: 現在の調達 + 追加
A18: 読み方
A19: 1. 『前提』B11 でシナリオを切り替える(1=楽観 / 2=標準 / 3=実行可能版)
A20: 2. 『資金繰り』6行目の受注本数を、自分の見込みに書き換える
A21: 3. 『必要調達』の「推奨する調達総額」を見る。ここが今の調達額を超えていれば足りない
A22: 4. 最低残高がマイナスなら、その月に資金が尽きる。採用の開始月(『月次固定費』B列)を後ろに倒して調整する
A24: ※ このモデルは1年目のみ。2年目以降は『年次PL』シート。
A25: ※ 消費税(海外発注は仕入税額控除が取れない可能性)は未反映。税理士の確認後に原価へ上乗せしてください。

Sheet 年次PL
A1: E. 5年の損益計画(保守版)
A2: 単位: 万円 / 青字を書き換えると営業利益まで再計算されます
B4: 1年目 2026/10-2027/9 | C4: 2年目 | D4: 3年目 | E4: 4年目 | F4: 5年目
A5: 受注本数 | B5: 35 | C5: 180 | D5: 380 | E5: 650 | F5: 950
A6: 平均単価 | B6: 48 | C6: 52 | D6: 56 | E6: 58 | F6: 62
A7: 1本あたり原価 | B7: 22 | C7: 22 | D7: 21 | E7: 20 | F7: 19
A8: プロダクト売上(R4) | B8: 0 | C8: 0 | D8: 2000 | E8: 8000 | F8: 20000
A9: プロダクト原価率 | B9: 0.2 | C9: 0.2 | D9: 0.2 | E9: 0.2 | F9: 0.2
A10: 日本側の人員(期末) | B10: 3 | C10: 8 | D10: 16 | E10: 26 | F10: 38
A11: 1人あたり人件費(年・法定福利込) | B11: 720 | C11: 720 | D11: 720 | E11: 720 | F11: 720
A12: 期中の平均在籍率 | B12: 0.6 | C12: 0.7 | D12: 0.75 | E12: 0.8 | F12: 0.85
A13: その他の販管費 | B13: 1100 | C13: 1500 | D13: 3000 | E13: 5000 | F13: 12000
A15: 受託売上 | B15: =B5*B6 -> 1680 | C15: =C5*C6 -> 9360 | D15: =D5*D6 -> 21280 | E15: =E5*E6 -> 37700 | F15: =F5*F6 -> 58900
A16: プロダクト売上 | B16: =B8 -> 0 | C16: =C8 -> 0 | D16: =D8 -> 2000 | E16: =E8 -> 8000 | F16: =F8 -> 20000
A17: 売上高 | B17: =B15+B16 -> 1680 | C17: =C15+C16 -> 9360 | D17: =D15+D16 -> 23280 | E17: =E15+E16 -> 45700 | F17: =F15+F16 -> 78900
A18: 売上原価 | B18: =B5*B7+B8*B9 -> 770 | C18: =C5*C7+C8*C9 -> 3960 | D18: =D5*D7+D8*D9 -> 8380 | E18: =E5*E7+E8*E9 -> 14600 | F18: =F5*F7+F8*F9 -> 22050
A19: 売上総利益 | B19: =B17-B18 -> 910 | C19: =C17-C18 -> 5400 | D19: =D17-D18 -> 14900 | E19: =E17-E18 -> 31100 | F19: =F17-F18 -> 56850
A20: 粗利率 | B20: =IF(B17=0,0,B19/B17) -> 0.54166667 | C20: =IF(C17=0,0,C19/C17) -> 0.57692308 | D20: =IF(D17=0,0,D19/D17) -> 0.64003436 | E20: =IF(E17=0,0,E19/E17) -> 0.68052516 | F20: =IF(F17=0,0,F19/F17) -> 0.72053232
A21: 人件費 | B21: =B10*B11*B12 -> 1296 | C21: =C10*C11*C12 -> 4032 | D21: =D10*D11*D12 -> 8640 | E21: =E10*E11*E12 -> 14976 | F21: =F10*F11*F12 -> 23256
A22: その他の販管費 | B22: =B13 -> 1100 | C22: =C13 -> 1500 | D22: =D13 -> 3000 | E22: =E13 -> 5000 | F22: =F13 -> 12000
A23: 販管費 合計 | B23: =B21+B22 -> 2396 | C23: =C21+C22 -> 5532 | D23: =D21+D22 -> 11640 | E23: =E21+E22 -> 19976 | F23: =F21+F22 -> 35256
A24: 営業利益 | B24: =B19-B23 -> -1486 | C24: =C19-C23 -> -132 | D24: =D19-D23 -> 3260 | E24: =E19-E23 -> 11124 | F24: =F19-F23 -> 21594
A25: 営業利益率 | B25: =IF(B17=0,0,B24/B17) -> -0.88452381 | C25: =IF(C17=0,0,C24/C17) -> -0.014102564 | D25: =IF(D17=0,0,D24/D17) -> 0.14003436 | E25: =IF(E17=0,0,E24/E17) -> 0.24341357 | F25: =IF(F17=0,0,F24/F17) -> 0.27368821
A27: プロダクト比率 | B27: =IF(B17=0,0,B16/B17) -> 0 | C27: =IF(C17=0,0,C16/C17) -> 0 | D27: =IF(D17=0,0,D16/D17) -> 0.085910653 | E27: =IF(E17=0,0,E16/E17) -> 0.1750547 | F27: =IF(F17=0,0,F16/F17) -> 0.25348542
A28: 1人あたり売上 | B28: =IF(B10=0,0,B17/B10) -> 560 | C28: =IF(C10=0,0,C17/C10) -> 1170 | D28: =IF(D10=0,0,D17/D10) -> 1455 | E28: =IF(E10=0,0,E17/E10) -> 1757.6923 | F28: =IF(F10=0,0,F17/F10) -> 2076.3158
A30: ※ 1年目は『資金繰り』シートの月次と整合させてください(受注本数の合計)。
A31: ※ 消費税(海外発注は仕入税額控除が取れない可能性)は未反映。確定後に1本あたり原価へ上乗せする。
A32: ※ 支払利息・法人税は未計上。営業利益までのモデル。
