Workbook

Sheet サマリー
A1: AI映像制作事業 5年計画サマリー（Ver1.4）
A2: 単位：百万円。すべて数式で、「前提」シートを書き換えると連動する。⚠［仮置き］の前提に乗った計画であり、実績ではない。
A3: 項目 | C3: 1期 | D3: 2期 | E3: 3期 | F3: 4期 | G3: 5期 | H3: 備考
A4: 売上高 | C4: =損益計算書!C9 | D4: =損益計算書!D9 | E4: =損益計算書!E9 | F4: =損益計算書!F9 | G4: =損益計算書!G9 | H4: 5期 88.1億
A5: ① 映像制作 | C5: =損益計算書!C4 | D5: =損益計算書!D4 | E5: =損益計算書!E4 | F5: =損益計算書!F4 | G5: =損益計算書!G4 | H5: 5,594本 × 60万円。SAMの1.5%
A6: ② ツール外販 | C6: =損益計算書!C7 | D6: =損益計算書!D7 | E6: =損益計算書!E7 | F6: =損益計算書!F7 | G6: =損益計算書!G7 | H6: 法人600社＋個人17,000人。海外展開が前提
A7: ③ 越境C2C手数料 | C7: =損益計算書!C8 | D7: =損益計算書!D8 | E7: =損益計算書!E8 | F7: =損益計算書!F8 | G7: =損益計算書!G8 | H7: GMV 83億 × 18%
A8: 売上総利益 | C8: =損益計算書!C15 | D8: =損益計算書!D15 | E8: =損益計算書!E15 | F8: =損益計算書!F15 | G8: =損益計算書!G15
A9: 営業利益 | C9: =損益計算書!C25 | D9: =損益計算書!D25 | E9: =損益計算書!E25 | F9: =損益計算書!F25 | G9: =損益計算書!G25 | H9: 3期に損益分岐、4期に通期黒字
A10: 営業利益率 | C10: =損益計算書!C26 | D10: =損益計算書!D26 | E10: =損益計算書!E26 | F10: =損益計算書!F26 | G10: =損益計算書!G26
A11: 営業キャッシュフロー | C11: =資金計画!C14 | D11: =資金計画!D14 | E11: =資金計画!E14 | F11: =資金計画!F14 | G11: =資金計画!G14 | H11: 税・運転資本の後
A12: 期末キャッシュ残高 | C12: =資金計画!C22 | D12: =資金計画!D22 | E12: =資金計画!E22 | F12: =資金計画!F22 | G12: =資金計画!G22 | H12: 一度もマイナスにならないこと
A13: 社員数 | C13: =損益計算書!C29 | D13: =損益計算書!D29 | E13: =損益計算書!E29 | F13: =損益計算書!F29 | G13: =損益計算書!G29 | H13: 業務委託・BPOは含まない
A14: 売上 / 社員（万円） | C14: =損益計算書!C30 | D14: =損益計算書!D30 | E14: =損益計算書!E30 | F14: =損益計算書!F30 | G14: =損益計算書!G30 | H14: 5期 1.44億
A15: 人手に比例しない収益 比率 | C15: =損益計算書!C33 | D15: =損益計算書!D33 | E15: =損益計算書!E33 | F15: =損益計算書!F33 | G15: =損益計算書!G33 | H15: 5期 90%。受託と読まれないための中心指標
A16: 研究開発費 ÷ 売上 | C16: =損益計算書!C31 | D16: =損益計算書!D31 | E16: =損益計算書!E31 | F16: =損益計算書!F31 | G16: =損益計算書!G31 | H16: 5期 18.2%
A17: AX倍率 | C17: =損益計算書!C6 | D17: =損益計算書!D6 | E17: =損益計算書!E6 | F17: =損益計算書!F6 | G17: =損益計算書!G6 | H17: 計画の最重要前提［仮置き］。3倍でも成立する
A19: シード投資家（1.42億）のリターン
A20: ケース | C20: 時価総額(億) | D20: 取り分(億) | E20: 倍率 | F20: IRR | H20: 根拠
A21: ライン別・保守 | C21: ='資本政策とリターン'!E13 | D21: ='資本政策とリターン'!F13 | E21: ='資本政策とリターン'!G13 | F21: ='資本政策とリターン'!H13 | H21: ツール6倍＋C2C4倍＋制作1.5倍
A22: ライン別・中庸 | C22: ='資本政策とリターン'!E14 | D22: ='資本政策とリターン'!F14 | E22: ='資本政策とリターン'!G14 | F22: ='資本政策とリターン'!H14 | H22: ツール7倍＋C2C5倍＋制作2.0倍
A23: ライン別・強気 | C23: ='資本政策とリターン'!E15 | D23: ='資本政策とリターン'!F15 | E23: ='資本政策とリターン'!G15 | F23: ='資本政策とリターン'!H15 | H23: ツール8倍＋C2C6倍＋制作2.5倍
A24: 全社 PSR 4倍 | C24: ='資本政策とリターン'!E19 | D24: ='資本政策とリターン'!F19 | E24: ='資本政策とリターン'!G19 | F24: ='資本政策とリターン'!H19 | H24: 人手に比例しない収益90%を根拠にする
A25: 全社 PSR 5倍 | C25: ='資本政策とリターン'!E20 | D25: ='資本政策とリターン'!F20 | E25: ='資本政策とリターン'!G20 | F25: ='資本政策とリターン'!H20
A27: ⚠ 上の倍率は事業計画からの逆算であって、投資の推奨でも利回りの保証でもない。前提の多くは未実証（「出所と仮置き」シート参照）。

Sheet 前提
A1: 前提（ここだけを書き換える）
A2: 黄色のセルが入力。他のシートはすべてここを参照する数式なので、書き換えれば損益・資金繰り・リターンまで動く。区分が［仮置き］のものは未実証。
A3: 大分類 | B3: 項目 | C3: 1期 | D3: 2期 | E3: 3期 | F3: 4期 | G3: 5期 | H3: 単位 | I3: 区分 | J3: 備考・出所
A4: ① 映像制作 | B4: 受注本数 | C4: 54 | D4: 350 | E4: 1200 | F4: 2800 | G4: 5594 | H4: 本 | I4: ［仮置き］ | J4: 5期はSAMの1.5%。B案（Ver1.3の11,189本を半減）
B5: 平均単価 | C5: 50 | D5: 55 | E5: 60 | F5: 60 | G5: 60 | H5: 万円/本 | I5: 相場準拠 | J5: 動画幹事・ムビサクの制作費相場帯に基づく想定
B6: AX倍率 | C6: 1 | D6: 1.5 | E6: 2.2 | F6: 3 | G6: 4 | H6: 倍 | I6: ［仮置き］ | J6: 1人あたり制作本数の倍率。計画の最重要前提
A7: 1本あたり原価 | B7: 中国クリエイターへの支払 | C7: 12 | D7: 12 | E7: 12 | F7: 12 | G7: 12 | H7: 万円/本 | I7: ［仮置き］ | J7: CHINA_SOURCING.md
B8: 制作ディレクション（AX前） | C8: 20 | D8: 20 | E8: 20 | F8: 20 | G8: 20 | H8: 万円/本 | I8: ［仮置き］ | J8: 業務委託。成果物単位の支払なのでAX倍率で除される（8時間相当）
B9: AIツール・素材・レンダリング | C9: 2 | D9: 2 | E9: 2 | F9: 2 | G9: 2 | H9: 万円/本 | I9: ［仮置き］ | J9: クラウドGPU・ライセンス・素材
B10: 品質バッファ（作り直し） | C10: 1.5 | D10: 1.5 | E10: 1.5 | F10: 1.5 | G10: 1.5 | H10: 万円/本 | I10: ［仮置き］ | J10: 検収落ち分の引当
A11: ② ツール外販 | B11: 法人契約数 | C11: 0 | D11: 15 | E11: 100 | F11: 320 | G11: 600 | H11: 社 | I11: ［仮置き］ | J11: 3期以降は海外が前提。国内の制作会社だけでは届かない
B12: 法人ACV | C12: 0 | D12: 250 | E12: 280 | F12: 300 | G12: 320 | H12: 万円/年 | I12: ［仮置き］ | J12: チェックポイント・LoRA・工程ツール
B13: 個人契約数 | C13: 0 | D13: 0 | E13: 2000 | F13: 8000 | G13: 17000 | H13: 人 | I13: ［仮置き］ | J13: 同上
B14: 個人ACV | C14: 12 | D14: 12 | E14: 12 | F14: 12 | G14: 12 | H14: 万円/年 | I14: ［仮置き］ | J14: 月1万円相当
B15: 粗利率 | C15: 0.8 | D15: 0.8 | E15: 0.8 | F15: 0.8 | G15: 0.8 | H15: % | I15: ［仮置き］ | J15: ソフトウェア外販の一般水準
A16: ③ 越境C2C | B16: GMV（流通総額） | C16: 50 | D16: 400 | E16: 1600 | F16: 4500 | G16: 8300 | H16: 百万円 | I16: ［仮置き］ | J16: 5期83億。ココナラの流通高に迫る規模
B17: 手数料率 | C17: 0.18 | D17: 0.18 | E17: 0.18 | F17: 0.18 | G17: 0.18 | H17: % | I17: ［仮置き］ | J17: 収納代行型。当社は資金を保持しない
B18: 粗利率 | C18: 0.85 | D18: 0.85 | E18: 0.85 | F18: 0.85 | G18: 0.85 | H18: % | I18: ［仮置き］ | J18: 決済手数料控除後
A19: 費用 | B19: 研究開発費 | C19: 30 | D19: 120 | E19: 450 | F19: 1000 | G19: 1600 | H19: 百万円 | I19: ［仮置き］ | J19: クラウドGPU・ライセンス・データ基盤。AX倍率を上げ続けるための投資
B20: BPO（CS・運用） | C20: 0 | D20: 10 | E20: 120 | F20: 450 | G20: 1000 | H20: 百万円 | I20: ［仮置き］ | J20: 社員ではなく外部委託
B21: 獲得費（固定分） | C21: 6 | D21: 40 | E21: 90 | F21: 150 | G21: 200 | H21: 百万円 | I21: ［仮置き］ | J21: C2C発注者の獲得ほか
B22: 獲得費率（制作売上比） | C22: 0.06 | D22: 0.06 | E22: 0.06 | F22: 0.06 | G22: 0.06 | H22: % | I22: ［仮置き］ | J22: SALES_COST.md
B23: 獲得費率（ツール売上比） | C23: 0.15 | D23: 0.15 | E23: 0.15 | F23: 0.15 | G23: 0.15 | H23: % | I23: ［仮置き］ | J23: 営業・CS
B24: その他販管費率（売上比） | C24: 0.04 | D24: 0.04 | E24: 0.04 | F24: 0.04 | G24: 0.04 | H24: % | I24: ［仮置き］ | J24: オフィス・SaaS・法務・インフラ
B25: 法定福利費等の負担率 | C25: 1.16 | D25: 1.16 | E25: 1.16 | F25: 1.16 | G25: 1.16 | H25: 倍 | I25: ［仮置き］ | J25: 年収に対する会社負担（社会保険・採用教育の按分）
A26: 資金 | B26: 実効税率 | C26: 0.3 | D26: 0.3 | E26: 0.3 | F26: 0.3 | G26: 0.3 | H26: % | I26: ［仮置き］ | J26: 繰越欠損金の控除後に適用
B27: 売上債権 回転日数（制作） | C27: 60 | D27: 60 | E27: 60 | F27: 60 | G27: 60 | H27: 日 | I27: ［仮置き］ | J27: 検収後の入金サイト
B28: 仕入債務 回転日数（制作原価） | C28: 30 | D28: 30 | E28: 30 | F28: 30 | G28: 30 | H28: 日 | I28: ［仮置き］ | J28: 中国の制作パートナーへの支払サイト
B29: ツール外販の前受期間 | C29: 180 | D29: 180 | E29: 180 | F29: 180 | G29: 180 | H29: 日 | I29: ［仮置き］ | J29: 年額一括前受の平均残高。月額課金にすると0日になり資金繰りは厳しくなる
B30: 設備投資 | C30: 0 | D30: 0 | E30: 0 | F30: 0 | G30: 0 | H30: 百万円 | I30: 方針 | J30: クラウドGPU前提のため自社設備を持たない。GPU費用は研究開発費に計上
B31: 調達：シード | C31: 150 | D31: 0 | E31: 0 | F31: 0 | G31: 0 | H31: 百万円 | I31: 確定 | J31: J-KISS 1.42億 ＋ 代表個人の直接出資 0.08億
B32: 調達：シリーズA | C32: 0 | D32: 300 | E32: 0 | F32: 0 | G32: 0 | H32: 百万円 | I32: 計画 | J32: 2期。これが無いと2期末に資金ショートする
B33: 調達：借入 | C33: 0 | D33: 0 | E33: 0 | F33: 0 | G33: 0 | H33: 百万円 | I33: 方針 | J33: 借入はしない

Sheet 人員と人件費
A1: 人員と人件費（社員は極小）
A2: 制作ディレクション・CS・オペレーションは社員ではなく業務委託／BPO。社員は経営・モデル開発・各機能の統括・管理のみ。
A3: 職種 | B3: 年収(万円) | C3: 1期 | D3: 2期 | E3: 3期 | F3: 4期 | G3: 5期 | H3: 考え方
A4: 経営・CxO | B4: 900 | C4: 1 | D4: 1 | E4: 2 | F4: 3 | G4: 3 | H4: 代表＋CFO／CTO級
A5: モデル開発エンジニア | B5: 850 | C5: 2 | D5: 6 | E5: 16 | F5: 28 | G5: 40 | H5: AX倍率を上げ続ける中核。ここだけ厚くする
A6: 制作統括 | B6: 650 | C6: 1 | D6: 2 | E6: 3 | F6: 3 | G6: 3 | H6: 業務委託ディレクターの束ね役。本数に比例させない
A7: 事業開発・アライアンス | B7: 700 | C7: 1 | D7: 2 | E7: 4 | F7: 5 | G7: 6 | H7: 法人開拓・海外展開
A8: クリエイターネットワーク統括 | B8: 600 | C8: 1 | D8: 1 | E8: 2 | F8: 3 | G8: 3 | H8: 中国パートナー・登録クリエイター管理
A9: 管理・コーポレート | B9: 550 | C9: 0 | D9: 1 | E9: 2 | F9: 4 | G9: 6 | H9: 経理・法務・上場準備
A10: 社員数 合計 | C10: =SUM(C4:C9) | D10: =SUM(D4:D9) | E10: =SUM(E4:E9) | F10: =SUM(F4:F9) | G10: =SUM(G4:G9) | H10: ここが「社員は極小」の実数
A11: 人件費（百万円） | C11: =SUMPRODUCT($B$4:$B$9,C4:C9)*前提!$C$25/100 | D11: =SUMPRODUCT($B$4:$B$9,D4:D9)*前提!$D$25/100 | E11: =SUMPRODUCT($B$4:$B$9,E4:E9)*前提!$E$25/100 | F11: =SUMPRODUCT($B$4:$B$9,F4:F9)*前提!$F$25/100 | G11: =SUMPRODUCT($B$4:$B$9,G4:G9)*前提!$G$25/100
A12: 1人あたり人件費（万円） | C12: =IF(C10=0,0,C11*100/C10) | D12: =IF(D10=0,0,D11*100/D10) | E12: =IF(E10=0,0,E11*100/E10) | F12: =IF(F10=0,0,F11*100/F10) | G12: =IF(G10=0,0,G11*100/G10) | H12: 安い職種が社外に出るので平均単価は上がる。総額は抑えられる
A14: 参考：社員ではない人たち
A15: 区分 | C15: 1期 | D15: 2期 | E15: 3期 | F15: 4期 | G15: 5期 | H15: 考え方
A16: 業務委託ディレクション（人） | C16: =前提!$C$4*(1/120+1/90)/前提!$C$6 | D16: =前提!$D$4*(1/120+1/90)/前提!$D$6 | E16: =前提!$E$4*(1/120+1/90)/前提!$E$6 | F16: =前提!$F$4*(1/120+1/90)/前提!$F$6 | G16: =前提!$G$4*(1/120+1/90)/前提!$G$6 | H16: 従来の1本あたり人年（1/120＋1/90）をAX倍率で除す
A17: 中国クリエイター 稼働（人） | C17: =前提!$C$4/(36*前提!$C$6) | D17: =前提!$D$4/(36*前提!$D$6) | E17: =前提!$E$4/(36*前提!$E$6) | F17: =前提!$F$4/(36*前提!$F$6) | G17: =前提!$G$4/(36*前提!$G$6) | H17: 1人あたり年36本を前提［仮置き］

Sheet 損益計算書
A1: 5年損益計算書（単位：百万円）
A2: すべて数式。「前提」シートと「人員と人件費」シートを参照している。
A3: 項目 | C3: 1期 | D3: 2期 | E3: 3期 | F3: 4期 | G3: 5期 | H3: 備考
A4: ① 映像制作 | C4: =前提!$C$4*前提!$C$5/100 | D4: =前提!$D$4*前提!$D$5/100 | E4: =前提!$E$4*前提!$E$5/100 | F4: =前提!$F$4*前提!$F$5/100 | G4: =前提!$G$4*前提!$G$5/100 | H4: 受注本数 × 平均単価
A5: 受注本数（本） | C5: =前提!$C$4 | D5: =前提!$D$4 | E5: =前提!$E$4 | F5: =前提!$F$4 | G5: =前提!$G$4
A6: AX倍率 | C6: =前提!$C$6 | D6: =前提!$D$6 | E6: =前提!$E$6 | F6: =前提!$F$6 | G6: =前提!$G$6
A7: ② ツール外販 | C7: =前提!$C$11*前提!$C$12/100+前提!$C$13*前提!$C$14/100 | D7: =前提!$D$11*前提!$D$12/100+前提!$D$13*前提!$D$14/100 | E7: =前提!$E$11*前提!$E$12/100+前提!$E$13*前提!$E$14/100 | F7: =前提!$F$11*前提!$F$12/100+前提!$F$13*前提!$F$14/100 | G7: =前提!$G$11*前提!$G$12/100+前提!$G$13*前提!$G$14/100 | H7: 法人契約数×ACV ＋ 個人契約数×ACV
A8: ③ C2C手数料 | C8: =前提!$C$16*前提!$C$17 | D8: =前提!$D$16*前提!$D$17 | E8: =前提!$E$16*前提!$E$17 | F8: =前提!$F$16*前提!$F$17 | G8: =前提!$G$16*前提!$G$17 | H8: GMV × 手数料率
A9: 売上高 | C9: =C4+C7+C8 | D9: =D4+D7+D8 | E9: =E4+E7+E8 | F9: =F4+F7+F8 | G9: =G4+G7+G8
A11: 1本あたり原価（万円） | C11: =前提!$C$7+前提!$C$8/前提!$C$6+前提!$C$9+前提!$C$10 | D11: =前提!$D$7+前提!$D$8/前提!$D$6+前提!$D$9+前提!$D$10 | E11: =前提!$E$7+前提!$E$8/前提!$E$6+前提!$E$9+前提!$E$10 | F11: =前提!$F$7+前提!$F$8/前提!$F$6+前提!$F$9+前提!$F$10 | G11: =前提!$G$7+前提!$G$8/前提!$G$6+前提!$G$9+前提!$G$10 | H11: ディレクション費はAX倍率で除される。ここがAXの効き所
A12: ① 売上総利益 | C12: =C4*(1-C11/前提!$C$5) | D12: =D4*(1-D11/前提!$D$5) | E12: =E4*(1-E11/前提!$E$5) | F12: =F4*(1-F11/前提!$F$5) | G12: =G4*(1-G11/前提!$G$5)
A13: ② 売上総利益 | C13: =C7*前提!$C$15 | D13: =D7*前提!$D$15 | E13: =E7*前提!$E$15 | F13: =F7*前提!$F$15 | G13: =G7*前提!$G$15
A14: ③ 売上総利益 | C14: =C8*前提!$C$18 | D14: =D8*前提!$D$18 | E14: =E8*前提!$E$18 | F14: =F8*前提!$F$18 | G14: =G8*前提!$G$18
A15: 売上総利益 | C15: =C12+C13+C14 | D15: =D12+D13+D14 | E15: =E12+E13+E14 | F15: =F12+F13+F14 | G15: =G12+G13+G14
A16: （参考）売上原価 | C16: =C9-C15 | D16: =D9-D15 | E16: =E9-E15 | F16: =F9-F15 | G16: =G9-G15
A17: 粗利率 | C17: =IF(C9=0,0,C15/C9) | D17: =IF(D9=0,0,D15/D9) | E17: =IF(E9=0,0,E15/E9) | F17: =IF(F9=0,0,F15/F9) | G17: =IF(G9=0,0,G15/G9)
A19: 人件費（社員） | C19: ='人員と人件費'!C11 | D19: ='人員と人件費'!D11 | E19: ='人員と人件費'!E11 | F19: ='人員と人件費'!F11 | G19: ='人員と人件費'!G11 | H19: 社員のみ。業務委託・BPOは含まない
A20: 研究開発費 | C20: =前提!$C$19 | D20: =前提!$D$19 | E20: =前提!$E$19 | F20: =前提!$F$19 | G20: =前提!$G$19 | H20: AX倍率を上げ続けるための投資。ここを削ると計画が崩れる
A21: BPO（CS・運用） | C21: =前提!$C$20 | D21: =前提!$D$20 | E21: =前提!$E$20 | F21: =前提!$F$20 | G21: =前提!$G$20
A22: 獲得費 | C22: =C4*前提!$C$22+C7*前提!$C$23+前提!$C$21 | D22: =D4*前提!$D$22+D7*前提!$D$23+前提!$D$21 | E22: =E4*前提!$E$22+E7*前提!$E$23+前提!$E$21 | F22: =F4*前提!$F$22+F7*前提!$F$23+前提!$F$21 | G22: =G4*前提!$G$22+G7*前提!$G$23+前提!$G$21
A23: その他販管費 | C23: =C9*前提!$C$24 | D23: =D9*前提!$D$24 | E23: =E9*前提!$E$24 | F23: =F9*前提!$F$24 | G23: =G9*前提!$G$24
A24: 販売費・一般管理費 計 | C24: =SUM(C19:C23) | D24: =SUM(D19:D23) | E24: =SUM(E19:E23) | F24: =SUM(F19:F23) | G24: =SUM(G19:G23)
A25: 営業利益 | C25: =C15-C24 | D25: =D15-D24 | E25: =E15-E24 | F25: =F15-F24 | G25: =G15-G24
A26: 営業利益率 | C26: =IF(C9=0,0,C25/C9) | D26: =IF(D9=0,0,D25/D9) | E26: =IF(E9=0,0,E25/E9) | F26: =IF(F9=0,0,F25/F9) | G26: =IF(G9=0,0,G25/G9)
A28: 投資家が見る指標
A29: 社員数 | C29: ='人員と人件費'!C10 | D29: ='人員と人件費'!D10 | E29: ='人員と人件費'!E10 | F29: ='人員と人件費'!F10 | G29: ='人員と人件費'!G10
A30: 売上 / 社員（万円） | C30: =IF(C29=0,0,C9*100/C29) | D30: =IF(D29=0,0,D9*100/D29) | E30: =IF(E29=0,0,E9*100/E29) | F30: =IF(F29=0,0,F9*100/F29) | G30: =IF(G29=0,0,G9*100/G29) | H30: 国内SaaSの平均2,000〜4,000万との比較に使う
A31: 研究開発費 ÷ 売上 | C31: =IF(C9=0,0,C20/C9) | D31: =IF(D9=0,0,D20/D9) | E31: =IF(E9=0,0,E20/E9) | F31: =IF(F9=0,0,F20/F9) | G31: =IF(G9=0,0,G20/G9)
A32: 人手に比例しない収益 | C32: =C7+C8+C4*(1-1/前提!$C$6) | D32: =D7+D8+D4*(1-1/前提!$D$6) | E32: =E7+E8+E4*(1-1/前提!$E$6) | F32: =F7+F8+F4*(1-1/前提!$F$6) | G32: =G7+G8+G4*(1-1/前提!$G$6) | H32: ②＋③＋①のうちAXで人手から切れた分
A33: 同 比率 | C33: =IF(C9=0,0,C32/C9) | D33: =IF(D9=0,0,D32/D9) | E33: =IF(E9=0,0,E32/E9) | F33: =IF(F9=0,0,F32/F9) | G33: =IF(G9=0,0,G32/G9) | H33: 受託と読まれないための中心指標。5期で90%

Sheet 資金計画
A1: 資金計画・キャッシュフロー（単位：百万円）
A2: 営業利益からキャッシュ残高まで。運転資本と法人税を引いた後の、実際に手元に残る現金。
A3: 項目 | C3: 1期 | D3: 2期 | E3: 3期 | F3: 4期 | G3: 5期 | H3: 備考
A4: 営業利益 | C4: =損益計算書!C25 | D4: =損益計算書!D25 | E4: =損益計算書!E25 | F4: =損益計算書!F25 | G4: =損益計算書!G25
A5: 繰越欠損金（期首） | C5: =0 | D5: =MAX(0,C5-C4) | E5: =MAX(0,D5-D4) | F5: =MAX(0,E5-E4) | G5: =MAX(0,F5-F4) | H5: 前期までの累積赤字。黒字化後の税負担を軽くする
A6: 課税所得 | C6: =MAX(0,C4-C5) | D6: =MAX(0,D4-D5) | E6: =MAX(0,E4-E5) | F6: =MAX(0,F4-F5) | G6: =MAX(0,G4-G5)
A7: 法人税等 | C7: =C6*前提!$C$26 | D7: =D6*前提!$D$26 | E7: =E6*前提!$E$26 | F7: =F6*前提!$F$26 | G7: =G6*前提!$G$26 | H7: 実効税率30%［仮置き］。繰越欠損金の控除後
A9: 運転資本：制作（売掛−買掛） | C9: =損益計算書!C4*前提!$C$27/365-(損益計算書!C4-損益計算書!C12)*前提!$C$28/365 | D9: =損益計算書!D4*前提!$D$27/365-(損益計算書!D4-損益計算書!D12)*前提!$D$28/365 | E9: =損益計算書!E4*前提!$E$27/365-(損益計算書!E4-損益計算書!E12)*前提!$E$28/365 | F9: =損益計算書!F4*前提!$F$27/365-(損益計算書!F4-損益計算書!F12)*前提!$F$28/365 | G9: =損益計算書!G4*前提!$G$27/365-(損益計算書!G4-損益計算書!G12)*前提!$G$28/365 | H9: 制作は入金60日・支払30日なので、伸びるほど現金が先に出る
A10: 運転資本：ツール前受金（△） | C10: =-損益計算書!C7*前提!$C$29/365 | D10: =-損益計算書!D7*前提!$D$29/365 | E10: =-損益計算書!E7*前提!$E$29/365 | F10: =-損益計算書!F7*前提!$F$29/365 | G10: =-損益計算書!G7*前提!$G$29/365 | H10: 年額一括前受なので資金の source になる。月額課金にすると消える
A11: 運転資本 残高 計 | C11: =C9+C10 | D11: =D9+D10 | E11: =E9+E10 | F11: =F9+F10 | G11: =G9+G10
A12: 運転資本の増減（△は流出） | C12: =-C11 | D12: =-(D11-C11) | E12: =-(E11-D11) | F12: =-(F11-E11) | G12: =-(G11-F11)
A14: 営業キャッシュフロー | C14: =C4-C7+C12 | D14: =D4-D7+D12 | E14: =E4-E7+E12 | F14: =F4-F7+F12 | G14: =G4-G7+G12
A15: 投資キャッシュフロー | C15: =-前提!$C$30 | D15: =-前提!$D$30 | E15: =-前提!$E$30 | F15: =-前提!$F$30 | G15: =-前提!$G$30 | H15: クラウドGPU前提のため自社設備を持たない
A16: 調達：シード | C16: =前提!$C$31 | D16: =前提!$D$31 | E16: =前提!$E$31 | F16: =前提!$F$31 | G16: =前提!$G$31
A17: 調達：シリーズA | C17: =前提!$C$32 | D17: =前提!$D$32 | E17: =前提!$E$32 | F17: =前提!$F$32 | G17: =前提!$G$32
A18: 調達：借入 | C18: =前提!$C$33 | D18: =前提!$D$33 | E18: =前提!$E$33 | F18: =前提!$F$33 | G18: =前提!$G$33 | H18: 借入はしない
A19: 財務キャッシュフロー | C19: =C16+C17+C18 | D19: =D16+D17+D18 | E19: =E16+E17+E18 | F19: =F16+F17+F18 | G19: =G16+G17+G18
A21: 当期キャッシュ増減 | C21: =C14+C15+C19 | D21: =D14+D15+D19 | E21: =E14+E15+E19 | F21: =F14+F15+F19 | G21: =G14+G15+G19
A22: 期末キャッシュ残高 | C22: =C21 | D22: =C22+D21 | E22: =D22+E21 | F22: =E22+F21 | G22: =F22+G21 | H22: ここがマイナスになる期があってはいけない
A24: 月次バーン（平均） | C24: =IF(C14>=0,0,-C14/12) | D24: =IF(D14>=0,0,-D14/12) | E24: =IF(E14>=0,0,-E14/12) | F24: =IF(F14>=0,0,-F14/12) | G24: =IF(G14>=0,0,-G14/12)
A25: ランウェイ（ヶ月） | C25: =IF(C24=0,"—",C22/C24) | D25: =IF(D24=0,"—",D22/D24) | E25: =IF(E24=0,"—",E22/E24) | F25: =IF(F24=0,"—",F22/F24) | G25: =IF(G24=0,"—",G22/G24) | H25: 期末残高 ÷ 月次バーン。黒字化後は「—」
A26: （感応度）前受金ゼロなら期末残高 | C26: =C22+C10 | D26: =D22+D10 | E26: =E22+E10 | F26: =F22+F10 | G26: =G22+G10 | H26: ツールを月額課金にした場合。ここもプラスなら資金繰りは前受に依存していない
A28: シード1.5億は何に使うか（1期の支出）
A29: 用途 | C29: 金額 | H29: 内容
A30: 研究開発費 | C30: =損益計算書!C20 | H30: モデル開発・クラウドGPU・データ基盤。ここが事業の本体
A31: 人件費（社員6名） | C31: =損益計算書!C19 | H31: 経営1・モデル開発2・制作統括1・事業開発1・クリエイター統括1
A32: 制作原価 | C32: =損益計算書!C4-損益計算書!C12 | H32: 中国クリエイターへの支払・業務委託ディレクション
A33: 獲得費 | C33: =損益計算書!C22 | H33: 初期案件の獲得・C2C発注者の獲得
A34: その他販管費 | C34: =損益計算書!C23 | H34: オフィス・SaaS・法務
A35: 1期の支出 計 | C35: =SUM(C30:C34)
A36: △ 1期の売上入金 | C36: =-損益計算書!C9 | H36: 制作・C2Cの入金。売掛のずれは上の運転資本で調整
A37: 1期の正味所要資金 | C37: =C35+C36
A38: 2期の正味所要資金 | C38: =-D14 | H38: シードだけでは2期を通せない。シリーズA3億は2期に必須
A40: ⚠ 3期は営業赤字だが、ツールの前受金が増えるため営業キャッシュフローは黒字になる。前受が無い（月額課金の）前提でも残高はプラスを保つ設計。

Sheet 原価とAX感応度
A1: AX倍率を変えると、5期の利益はどう動くか
A2: AXは人数ではなく「1本あたりのディレクション時間」に効く。業務委託は成果物単位の支払なので、時間が1/4になれば単価も1/4になる。
A3: AX倍率 | B3: ディレクション費/本 | C3: 1本あたり原価 | D3: 制作の粗利率 | E3: 5期 営業利益(百万) | F3: 営業利益率 | G3: 判定
A4: 1 | B4: =前提!$G$8/A4 | C4: =前提!$G$7+B4+前提!$G$9+前提!$G$10 | D4: =1-C4/前提!$G$5 | E4: =損益計算書!$G$4*D4+損益計算書!$G$13+損益計算書!$G$14-損益計算書!$G$24 | F4: =E4/損益計算書!$G$9 | G4: AXなし。それでも黒字だが、投資家が払う倍率は付かない
A5: 2 | B5: =前提!$G$8/A5 | C5: =前提!$G$7+B5+前提!$G$9+前提!$G$10 | D5: =1-C5/前提!$G$5 | E5: =損益計算書!$G$4*D5+損益計算書!$G$13+損益計算書!$G$14-損益計算書!$G$24 | F5: =E5/損益計算書!$G$9
A6: 3 | B6: =前提!$G$8/A6 | C6: =前提!$G$7+B6+前提!$G$9+前提!$G$10 | D6: =1-C6/前提!$G$5 | E6: =損益計算書!$G$4*D6+損益計算書!$G$13+損益計算書!$G$14-損益計算書!$G$24 | F6: =E6/損益計算書!$G$9 | G6: ◀ ここでも計画は成立する（本数を半減させた効果）
A7: 4 | B7: =前提!$G$8/A7 | C7: =前提!$G$7+B7+前提!$G$9+前提!$G$10 | D7: =1-C7/前提!$G$5 | E7: =損益計算書!$G$4*D7+損益計算書!$G$13+損益計算書!$G$14-損益計算書!$G$24 | F7: =E7/損益計算書!$G$9 | G7: ◀ 計画値
A8: 5 | B8: =前提!$G$8/A8 | C8: =前提!$G$7+B8+前提!$G$9+前提!$G$10 | D8: =1-C8/前提!$G$5 | E8: =損益計算書!$G$4*D8+損益計算書!$G$13+損益計算書!$G$14-損益計算書!$G$24 | F8: =E8/損益計算書!$G$9 | G8: 上振れ
A10: AXは原価を下げる装置であり、利益率そのものを作る。浮いた分は研究開発に戻してAX倍率をさらに上げる。この循環が、競合に同じ年数を要求する。

Sheet 資本構成の推移
A1: 株式シェアの推移（設立 → 上場）
A2: 出所は CAP_TABLE.md 第5章。J-KISS はポストマネー・キャップなので、転換時のシード持分は 調達額 ÷ キャップ。
A3: 項目 | C3: 値 | D3: 単位 | E3: 区分 | J3: 備考
A4: 資本金 | B4: 資本金 | C4: 800 | D4: 万円 | E4: 確定 | J4: 代表個人が全額出資
B5: ESOP枠（設立時） | C5: 0.1 | D5: % | E5: 計画 | J5: 後から作ると既存株主全員の希薄化になるので設立時に設計する
B6: J-KISS キャップ（ポストマネー） | C6: 6 | D6: 億円 | E6: 確定 | J6: 交渉帯は6〜10億。低すぎるとシリーズAで一気に薄まる
B7: シード調達額 | C7: 1.42 | D7: 億円 | E7: 確定 | J7: 目標1.5億のうち0.08億は代表個人の直接出資
B8: ディスカウント | C8: 0.2 | D8: % | E8: 確定 | J8: キャップとの有利な方が適用される
B9: シリーズA ポストマネー評価 | C9: 15 | D9: 億円 | E9: 計画 | J9: 2028年（2期）
B10: シリーズA 調達額 | C10: 3 | D10: 億円 | E10: 計画 | J10: これが無いと2期末に資金ショートする
B11: ESOP補充後の ESOP比率 | C11: 0.099 | D11: % | E11: 計画 | J11: シリーズAで薄まった枠を戻す
B12: IPO 公募比率 | C12: 0.2 | D12: % | E12: 計画 | J12: 2031年。流通株式25%を満たすには要見直し（下表）
B13: 転換時のシード持分（シリーズA前） | C13: =C7/C6 | J13: ポストマネー・キャップなので 1.42億 ÷ 6億
B14: シリーズA の持分 | C14: =C10/C9 | J14: 3億 ÷ post 15億
A16: 持分の推移
A17: 時期 | B17: イベント | C17: 金額 | D17: 創業者 | E17: ESOP | F17: シード | G17: シリーズA | H17: 公募 | I17: 合計 | J17: 経営権の判定
A18: 2026/10 | B18: 設立（資本金800万） | C18: — | D18: =1 | E18: =0 | F18: =0 | G18: =0 | H18: =0 | I18: =SUM(D18:H18) | J18: =IF(D18>0.5,"経営権あり（50%超）",IF(D18>0.334,"拒否権あり（1/3超）","1/3割れ"))
A19: 2026/10 | B19: ESOP枠を設計 | C19: — | D19: =D18*(1-$C$5) | E19: =$C$5 | F19: =0 | G19: =0 | H19: =0 | I19: =SUM(D19:H19) | J19: =IF(D19>0.5,"経営権あり（50%超）",IF(D19>0.334,"拒否権あり（1/3超）","1/3割れ"))
A20: 2026/10 | B20: J-KISS 発行（未転換） | C20: 1.42億 | D20: =D19 | E20: =E19 | F20: =0 | G20: =0 | H20: =0 | I20: =SUM(D20:H20) | J20: =IF(D20>0.5,"経営権あり（50%超）",IF(D20>0.334,"拒否権あり（1/3超）","1/3割れ"))
A21: 2028 | B21: シリーズA ＋ J-KISS転換 | C21: 3億 | D21: =D20*(1-$C$13)*(1-$C$14) | E21: =E20*(1-$C$13)*(1-$C$14) | F21: =$C$13*(1-$C$14) | G21: =$C$14 | H21: =0 | I21: =SUM(D21:H21) | J21: =IF(D21>0.5,"経営権あり（50%超）",IF(D21>0.334,"拒否権あり（1/3超）","1/3割れ"))
A22: 2028 | B22: ESOP補充 | C22: — | D22: =D21*(1-$C$11)/(1-E21) | E22: =$C$11 | F22: =F21*(1-$C$11)/(1-E21) | G22: =G21*(1-$C$11)/(1-E21) | H22: =0 | I22: =SUM(D22:H22) | J22: =IF(D22>0.5,"経営権あり（50%超）",IF(D22>0.334,"拒否権あり（1/3超）","1/3割れ"))
A23: 2031 | B23: IPO 公募 | C23: — | D23: =D22*(1-$C$12) | E23: =E22*(1-$C$12) | F23: =F22*(1-$C$12) | G23: =G22*(1-$C$12) | H23: =$C$12 | I23: =SUM(D23:H23) | J23: =IF(D23>0.5,"経営権あり（50%超）",IF(D23>0.334,"拒否権あり（1/3超）","1/3割れ"))
B24: J-KISS は転換までは議決権が発生しない。1/3の線を踏まずに済むのが J-KISS を選ぶ理由のひとつ。
A26: 上場時の評価額
A27: 株主 | B27: 上場時持分 | D27: 保守 348億 | E27: 中庸 419億 | F27: 強気 490億 | J27: 備考
A28: 創業者 | B28: =D23 | D28: =B28*348 | E28: =B28*419 | F28: =B28*490 | J28: 経営権は上場時に50%を割る。ただしシリーズA後も52.7%を維持できる
A29: シード投資家 | B29: =F23 | D29: =B29*348 | E29: =B29*419 | F29: =B29*490 | J29: 出資1.42億に対する取り分
A30: シリーズA | B30: =G23 | D30: =B30*348 | E30: =B30*419 | F30: =B30*490
A31: ESOP | B31: =E23 | D31: =B31*348 | E31: =B31*419 | F31: =B31*490 | J31: 役員・従業員への配分枠
A32: 公募 | B32: =H23 | D32: =B32*348 | E32: =B32*419 | F32: =B32*490
A33: 単位は億円。時価総額は「資本政策とリターン」シートのライン別評価。
A35: ⚠ 流通株式比率 — このままでは基準25%を満たさない
A36: 株主 | B36: 上場時持分 | D36: 流通株式への算入 | J36: 理由
A37: 創業者（役員） | B37: =D23 | D37: × 除外 | J37: 役員は除外
A38: シード投資家 | B38: =F23 | D38: × 除外 | J38: 10%超のため除外
A39: シリーズA | B39: =G23 | D39: × 除外 | J39: 10%超のため除外
A40: ESOP | B40: =E23 | D40: × 除外 | J40: 役員・従業員分は除外
A41: 公募 | B41: =H23 | D41: ○ 算入 | J41: 算入
A42: 流通株式比率 | B42: =H23 | D42: =B42-0.25 | J42: 基準25%に対する過不足
A44: 手当て: ①公募を25%に引き上げる（創業者42.2%→39.5%）／②公募20%＋売出し5〜8%を併用（推奨）／③上場前にVC持分を10%未満へ分散。主幹事証券が決まる4期に確定させる論点。シードのタームシートに「上場時の売出しに協力する」条項を入れておくこと。

Sheet 資本政策とリターン
A1: 資本政策とシード投資家のリターン
A2: ⚠ 事業計画からの逆算であって、投資の推奨でも利回りの保証でもない。計画が達成された場合の数字。
A3: 項目 | B3: 値 | C3: 単位 | D3: 区分 | I3: 備考
A4: J-KISS キャップ（ポストマネー） | B4: ='資本構成の推移'!C6 | C4: 億円 | D4: 確定 | I4: 「資本構成の推移」シートの入力を参照
A5: シード調達額 | B5: ='資本構成の推移'!C7 | C5: 億円 | D5: 確定 | I5: 目標1.5億のうち0.08億は代表個人が直接出資
A6: 転換時のシード持分 | B6: ='資本構成の推移'!C13 | C6: % | D6: 計算 | I6: ポストマネー・キャップなので ＝ 調達額 ÷ キャップ
A7: 転換後の希薄化 | B7: =B8/B6 | C7: 倍 | D7: 計算 | I7: シリーズA20% → ESOP補充 → IPO公募20% の積。推移シートから逆算
A8: 上場後のシード持分 | B8: ='資本構成の推移'!F23 | C8: % | D8: 計算 | I8: CAP_TABLE.md 第5章
A9: 出資 → 上場 | B9: 4.9 | C9: 年 | D9: 計画 | I9: 2026年10月出資 → 2031年9月 東証グロース
A11: ① ライン別に倍率を分けた場合（証券会社が実際にやる見方）
A12: ケース | B12: ツール倍率 | C12: C2C倍率 | D12: 制作倍率 | E12: 時価総額(億) | F12: 取り分(億) | G12: 倍率 | H12: IRR | I12: 考え方
A13: 保守 | B13: 6 | C13: 4 | D13: 1.5 | E13: =(損益計算書!$G$7*B13+損益計算書!$G$8*C13+損益計算書!$G$4*D13)/100 | F13: =E13*$B$8 | G13: =F13/$B$5 | H13: =G13^(1/$B$9)-1 | I13: 人手に比例しない90%を根拠に、ツールへSaaS寄りの倍率を当てる
A14: 中庸 | B14: 7 | C14: 5 | D14: 2 | E14: =(損益計算書!$G$7*B14+損益計算書!$G$8*C14+損益計算書!$G$4*D14)/100 | F14: =E14*$B$8 | G14: =F14/$B$5 | H14: =G14^(1/$B$9)-1
A15: 強気 | B15: 8 | C15: 6 | D15: 2.5 | E15: =(損益計算書!$G$7*B15+損益計算書!$G$8*C15+損益計算書!$G$4*D15)/100 | F15: =E15*$B$8 | G15: =F15/$B$5 | H15: =G15^(1/$B$9)-1 | I15: Synthesia・HeyGenと同じ土俵に立てた場合
A17: ② 全社に PSR を当てた場合
A18: ケース | B18: PSR | E18: 時価総額(億) | F18: 取り分(億) | G18: 倍率 | H18: IRR | I18: 考え方
A19: PSR 4倍 | B19: 4 | E19: =損益計算書!$G$9*B19/100 | F19: =E19*$B$8 | G19: =F19/$B$5 | H19: =G19^(1/$B$9)-1 | I19: 人手に比例しない収益が90%であることを根拠にする
A20: PSR 5倍 | B20: 5 | E20: =損益計算書!$G$9*B20/100 | F20: =E20*$B$8 | G20: =F20/$B$5 | H20: =G20^(1/$B$9)-1
A22: ⚠ 東証グロースの維持基準「上場5年経過後に時価総額100億円」に対し、保守ケースでも3倍以上のバッファ。ただし計画が達成された場合に限る。

Sheet 業界ベンチマーク
A1: 実在企業と並べる（5期の当社）
A2: ⚠ 世界の「映像制作会社ランキング」は存在しない。大手広告グループは制作事業を分離開示しないため、比較できるのは開示のある会社に限られる。
A3: 会社 | B3: 売上(億円) | C3: 区分 | D3: 決算期・出所 | E3: 備考
A4: 東映 | B4: 1853 | C4: 映画・映像製作 | D4: 2026/3期 | E4: 国内最大。劇場・テレビ・版権
A5: IMAGICA GROUP | B5: 1000 | C5: ポスプロ・映像技術 | D5: 2026/3期（Q1 222億からの推計） | E5: 推計値
A6: 東映アニメーション | B6: 937 | C6: アニメ製作 | D6: 2026/3期
A7: AOI TYO Holdings | B7: 511 | C7: 広告・企業映像 | D7: 2020/12期 | E7: その後 非公開化
A8: 東北新社 | B8: 477 | C8: 広告・企業映像 | D8: 2026/3期 | E8: 当社①制作33.6億の比較対象
A9: HeyGen | B9: 300 | C9: AI動画・ARR | D9: $200M（1ドル150円換算） | E9: $100M→$200M を8ヶ月
A10: Synthesia | B10: 210 | C10: AI動画・ARR | D10: $140M（1ドル150円換算） | E10: 当社②ツール39.6億の比較対象
A11: IG Port | B11: 141 | C11: アニメ製作 | D11: 2026/5期
A12: Runway | B12: 非開示 | C12: AI動画 | D12: 非開示 | E12: 売上を公表していない
A13: Technicolor | B13: 非開示 | C13: VFX・ポスプロ | D13: 2026年 経営破綻 | E13: 上場していた制作会社は消えつつある
A14: 【当社 5期（2031年）】 | B14: =損益計算書!$G$9/100 | C14: ①制作＋②ツール＋③C2C | D14: 本計画 | E14: 東北新社477億の約18%。うち①制作は33.6億（同7%）
A16: ① 制作 ÷ 東北新社 | B16: =損益計算書!$G$4/100/477
A17: ② ツール ÷ Synthesia | B17: =損益計算書!$G$7/100/210

Sheet 出所と仮置き
A1: 数字の出所と、［仮置き］の一覧
A2: 投資家に聞かれて最初に困るのがここ。実測値と仮置きを混ぜないこと。
A3: 項目 | B3: 値 | C3: 区分 | D3: 出所・根拠
A4: 国内 映像制作市場 | B4: 4,580億円 | C4: 実測 | D4: 矢野経済研究所（BtoB映像制作）。動画コンテンツ市場6,300億とは別枠
A5: 制作費の相場帯 | B5: 10〜500万円/本 | C5: 実測 | D5: 動画幹事・ムビサク（用途別の制作費相場）
A6: AI導入による削減率 | B6: ▲50〜90% | C6: 当社試算 | D6: 工程別削減率（企画▲50・撮影▲80・機材▲80・出演▲90・編集▲50・諸経費▲30）を費用構成に当てたもの
A7: 東証グロース 上場維持基準 | B7: 5年経過後 時価総額100億円 | C7: 実測 | D7: 日本取引所グループ。上場基準は改定が続くため準備期に再確認する
A8: ベンチマーク各社の売上 | B8: 「業界ベンチマーク」シート | C8: 実測 | D8: 各社の有価証券報告書・決算短信。ARRは各社公表値、1ドル150円換算
A9: スキルシェア市場の映像比率 | B9: 非公表 | C9: 確認不能 | D9: ココナラ決算・矢野経済のいずれも映像分野を分離開示していない
A10: ──────────
A11: AX倍率 | B11: 1.0 → 4.0倍 | C11: ［仮置き］ | D11: 未実証。計画の最重要前提。3倍でも営業利益率23.3%で成立することを確認済み
A12: 受注本数カーブ | B12: 54 → 5,594本 | C12: ［仮置き］ | D12: 5期でSAMの1.5%。市場が制約ではなく、作る人が制約
A13: 1本あたり原価の内訳 | B13: 20.5万円（AX4倍時） | C13: ［仮置き］ | D13: 中国クリエイター12＋ディレクション5＋ツール2＋バッファ1.5
A14: ツール外販の契約数 | B14: 法人600社／個人17,000人 | C14: ［仮置き］ | D14: 国内の制作会社だけでは届かない。海外展開が前提
A15: C2C の GMV | B15: 83億円 | C15: ［仮置き］ | D15: ココナラの流通高に迫る規模。自動化が効いていることが前提
A16: 手数料率 | B16: 18% | C16: ［仮置き］ | D16: 収納代行型。資金決済法の該当性は弁護士に確認中
A17: 研究開発費 | B17: 5期 16億 | C17: ［仮置き］ | D17: クラウドGPU・ライセンス・データ基盤
A18: 実効税率 | B18: 30% | C18: ［仮置き］ | D18: 繰越欠損金の控除後に適用。税理士に確認する
A19: 入金・支払サイト | B19: 売掛60日／買掛30日 | C19: ［仮置き］ | D19: 契約前。ここが延びると資金繰りに直撃する
A20: ツール外販の前受期間 | B20: 180日 | C20: ［仮置き］ | D20: 年額一括前受の平均残高。月額課金にすると0日になり、資金計画が変わる
A21: J-KISS キャップ | B21: 6億円（ポストマネー） | C21: 確定 | D21: CAP_TABLE.md 第4章。交渉帯6〜10億。転換時のシード持分は 1.42÷6＝23.7%
A22: シリーズA の評価 | B22: post 15億・調達3億 | C22: 計画 | D22: CAP_TABLE.md 第5章。未交渉。ここが下がると創業者持分も薄まる
... A26: 業務委託の契約設計 | B26: ─ | C26: 未着手 | D26: 偽装請負と読まれない設計が必要。1年目に弁護士と作成する
